LICENSE
NOTICE
README.md
requirements.txt
setup.py
baikal_sdk.egg-info/PKG-INFO
baikal_sdk.egg-info/SOURCES.txt
baikal_sdk.egg-info/dependency_links.txt
baikal_sdk.egg-info/not-zip-safe
baikal_sdk.egg-info/requires.txt
baikal_sdk.egg-info/top_level.txt
clients/__init__.py
clients/baikal_client.py
clients/cache.py
clients/exceptions.py
clients/aio/__init__.py
clients/aio/aiohttp_client.py
clients/aio/baikal_client.py