Metadata-Version: 2.1
Name: baikal-sdk
Version: 1.2.5
Summary: SDK to generate tokens for the 4th Platform
Home-page: https://github.com/Telefonica/baikal-sdk/python
Maintainer: 4th Platform team
Maintainer-email: 4pf@telefonica.com
License: Apache 2.0
Classifier: Programming Language :: Python :: 3.7
Classifier: Intended Audience :: Developers
Classifier: License :: OSI Approved :: Apache Software License
Classifier: Topic :: Security
Classifier: Topic :: Software Development :: Libraries :: Python Modules
License-File: LICENSE
License-File: NOTICE
